django_ulidfield/__init__.py
django_ulidfield/fields.py
django_ulidfield-0.1.0.dist-info/LICENSE
django_ulidfield-0.1.0.dist-info/METADATA
django_ulidfield-0.1.0.dist-info/WHEEL
django_ulidfield-0.1.0.dist-info/RECORD
