Metadata-Version: 2.3
Name: django-ulidfield
Version: 0.1.0
Summary: A drop-in Django model field for storing sortable, time-encoded ULIDs as 26-character strings.
License: MIT
Author: Christian Gonzalez
Author-email: christiangonzalezblack@gmail.com
Requires-Python: >=3.9
Classifier: License :: OSI Approved :: MIT License
Classifier: Programming Language :: Python :: 3
Classifier: Programming Language :: Python :: 3.9
Classifier: Programming Language :: Python :: 3.10
Classifier: Programming Language :: Python :: 3.11
Classifier: Programming Language :: Python :: 3.12
Classifier: Programming Language :: Python :: 3.13
Requires-Dist: django (>=4.2,<5.3)
Requires-Dist: python-ulid (>=3.0.0,<4.0.0)
